.codeclimate.yml
.codecov.yml
.coveragerc
.gitignore
.gitlab-ci.yml
LICENSE
MANIFEST.in
Makefile
README.md
VERSION
gitlab-ci-test.sh
manage.py
pytest.ini
requirements.txt
setup.cfg
setup.py
test_settings.py
tox.ini
django_auto_url/__init__.py
django_auto_url/admin.py
django_auto_url/apps.py
django_auto_url.egg-info/PKG-INFO
django_auto_url.egg-info/SOURCES.txt
django_auto_url.egg-info/dependency_links.txt
django_auto_url.egg-info/requires.txt
django_auto_url.egg-info/top_level.txt
django_auto_url/kwargs/__init__.py
django_auto_url/kwargs/kwargs.py
django_auto_url/migrations/__init__.py
django_auto_url/mixins/__init__.py
django_auto_url/mixins/mixins.py
django_auto_url/templatetags/__init__.py
django_auto_url/templatetags/auto_url.py
django_auto_url/tests/__init__.py
django_auto_url/tests/conftest.py
django_auto_url/tests/factories.py
django_auto_url/tests/models.py
django_auto_url/tests/sub_urls_for_test.py
django_auto_url/tests/test_bad_index.py
django_auto_url/tests/test_simple.py
django_auto_url/tests/urls_for_bad_index_tests.py
django_auto_url/tests/urls_for_tests.py
django_auto_url/tests/utils.py
django_auto_url/tests/migrations/0001_initial.py
django_auto_url/tests/migrations/__init__.py
django_auto_url/tests/templates/generic.html
django_auto_url/tests/templates/index.html
django_auto_url/tests/templates/link_target_from_context.html
django_auto_url/tests/templates/string_object.html
django_auto_url/tests/templates/use_kwargs.html
django_auto_url/tests/templates/with_args_link.html
django_auto_url/tests/templates/with_links.html
django_auto_url/tests/views/__init__.py
django_auto_url/tests/views/test_bad_index_view.py
django_auto_url/tests/views/test_invalid_kwargs_view.py
django_auto_url/tests/views/test_sub_views.py
django_auto_url/tests/views/test_views.py
django_auto_url/urls/__init__.py
django_auto_url/urls/urls.py
django_auto_url/utils/__init__.py
django_auto_url/utils/class2urlname.py
django_auto_url/utils/lazy.py
doc/Makefile
doc/make.bat
doc/source/conf.py
doc/source/index.rst
doc/source/links.rst
doc/source/reference.rst
doc/source/_ext/th_djangodocs.py