Metadata-Version: 2.1
Name: django-auto-url
Version: 0.0.3
Summary: Automagic urls for Django
Home-page: https://gitlab.com/thht_django/django_auto_url
Author: Thomas Hartmann
Author-email: thomas.hartmann@th-ht.de
License: GPLv3
Keywords: Django URL
Classifier: Development Status :: 4 - Beta
Classifier: Framework :: Django
Classifier: Intended Audience :: Developers
Classifier: License :: OSI Approved :: GNU General Public License v3 (GPLv3)
Classifier: Operating System :: OS Independent
Classifier: Programming Language :: Python
License-File: LICENSE
